[[null,null,{"skillId":42,"type":"A","links":[6,12,8],"extraDescription":null,"reqLevel":1,"reqSP":1,"specialConditionText":"None","specialConditionSwitchId":0,"previewImage":"","previewGif":"","onClickActionMode":0,"onLerningCE":0,"learnedSwitchId":0},null,null,null,{"skillId":46,"type":"A","links":[10,16],"extraDescription":null,"reqLevel":1,"reqSP":1,"specialConditionText":"None","specialConditionSwitchId":0,"previewImage":"","previewGif":"","onClickActionMode":0,"onLerningCE":0,"learnedSwitchId":0},null,{"skillId":52,"type":"A","links":[13],"extraDescription":null,"reqLevel":1,"reqSP":1,"specialConditionText":"None","specialConditionSwitchId":0,"previewImage":"","previewGif":"","onClickActionMode":0,"onLerningCE":0,"learnedSwitchId":0},null,{"skillId":43,"type":"A","links":[],"extraDescription":null,"reqLevel":1,"reqSP":1,"specialConditionText":"None","specialConditionSwitchId":0,"previewImage":"","previewGif":"","onClickActionMode":0,"onLerningCE":0,"learnedSwitchId":0},null,{"skillId":48,"type":"A","links":[22],"extraDescription":null,"reqLevel":1,"reqSP":1,"specialConditionText":"None","specialConditionSwitchId":0,"previewImage":"","previewGif":"","onClickActionMode":0,"onLerningCE":0,"learnedSwitchId":0},{"skillId":44,"type":"A","links":[19,18],"extraDescription":null,"reqLevel":1,"reqSP":1,"specialConditionText":"None","specialConditionSwitchId":0,"previewImage":"","previewGif":"","onClickActionMode":0,"onLerningCE":0,"learnedSwitchId":0},null,null,{"skillId":47,"type":"A","links":[],"extraDescription":null,"reqLevel":1,"reqSP":1,"specialConditionText":"None","specialConditionSwitchId":0,"previewImage":"","previewGif":"","onClickActionMode":0,"onLerningCE":0,"learnedSwitchId":0},null,{"skillId":51,"type":"A","links":[],"extraDescription":null,"reqLevel":1,"reqSP":1,"specialConditionText":"None","specialConditionSwitchId":0,"previewImage":"","previewGif":"","onClickActionMode":0,"onLerningCE":0,"learnedSwitchId":0},{"skillId":45,"type":"A","links":[],"extraDescription":null,"reqLevel":1,"reqSP":1,"specialConditionText":"None","specialConditionSwitchId":0,"previewImage":"","previewGif":"","onClickActionMode":0,"onLerningCE":0,"learnedSwitchId":0},null,null,{"skillId":49,"type":"A","links":[27],"extraDescription":null,"reqLevel":1,"reqSP":1,"specialConditionText":"None","specialConditionSwitchId":0,"previewImage":"","previewGif":"","onClickActionMode":0,"onLerningCE":0,"learnedSwitchId":0},null,null,null,null,{"skillId":50,"type":"A","links":[],"extraDescription":null,"reqLevel":1,"reqSP":1,"specialConditionText":"None","specialConditionSwitchId":0,"previewImage":"","previewGif":"","onClickActionMode":0,"onLerningCE":0,"learnedSwitchId":0}]]